{
  "version": "7",
  "dialect": "mysql",
  "entries": [
    {
      "idx": 0,
      "version": "5",
      "when": 1769568757599,
      "tag": "0000_lowly_mattie_franklin",
      "breakpoints": true
    },
    {
      "idx": 1,
      "version": "5",
      "when": 1769568966662,
      "tag": "0001_wandering_professor_monster",
      "breakpoints": true
    },
    {
      "idx": 2,
      "version": "5",
      "when": 1769569757855,
      "tag": "0002_modern_adam_destine",
      "breakpoints": true
    }
  ]
}